{
  "date": "2026-07-16",
  "ticker": "DFAW",
  "prior_date": "2026-07-15",
  "diff": [
    {
      "ticker": "DCOR US",
      "name": "DFA US CORE EQUITY 1 ETF",
      "identifier": "25434V625",
      "sector": "",
      "status": "changed",
      "quantity_today": 3354352.0,
      "quantity_prior": 3340032.0,
      "quantity_pct_change": 0.4287,
      "pct_of_fund_today": 17.755155,
      "pct_of_fund_prior": 17.715787,
      "pct_of_fund_change": 0.039368,
      "market_value_today": 277740345.6
    },
    {
      "ticker": "DFAC US",
      "name": "DFA US CORE EQUITY 2 ETF",
      "identifier": "25434V708",
      "sector": "",
      "status": "changed",
      "quantity_today": 18754030.0,
      "quantity_prior": 18674254.0,
      "quantity_pct_change": 0.4272,
      "pct_of_fund_today": 53.434621,
      "pct_of_fund_prior": 53.314214,
      "pct_of_fund_change": 0.120407,
      "market_value_today": 835867117.1
    },
    {
      "ticker": "DFEM US",
      "name": "DFA EM CORE EQUITY 2 ETF",
      "identifier": "25434V732",
      "sector": "",
      "status": "changed",
      "quantity_today": 3519467.0,
      "quantity_prior": 3504955.0,
      "quantity_pct_change": 0.414,
      "pct_of_fund_today": 8.641849,
      "pct_of_fund_prior": 8.768027,
      "pct_of_fund_change": -0.126178,
      "market_value_today": 135182727.47
    },
    {
      "ticker": "DFGR US",
      "name": "DFA GBL REAL ESTATE ETF",
      "identifier": "25434V658",
      "sector": "",
      "status": "changed",
      "quantity_today": 904793.0,
      "quantity_prior": 900841.0,
      "quantity_pct_change": 0.4387,
      "pct_of_fund_today": 1.727706,
      "pct_of_fund_prior": 1.692471,
      "pct_of_fund_change": 0.035235,
      "market_value_today": 27026166.91
    },
    {
      "ticker": "DFIC US",
      "name": "DFA INTL CORE EQTY 2 ETF",
      "identifier": "25434V799",
      "sector": "",
      "status": "changed",
      "quantity_today": 7659321.0,
      "quantity_prior": 7628665.0,
      "quantity_pct_change": 0.4019,
      "pct_of_fund_today": 18.381038,
      "pct_of_fund_prior": 18.453992,
      "pct_of_fund_change": -0.072954,
      "market_value_today": 287530910.34
    }
  ]
}